{
	"info": {
		"_postman_id": "ad14ea95-a182-49e7-a31b-cd641550fbfc",
		"name": "Course App",
		"schema": "https://schema.getpostman.com/json/collection/v2.1.0/collection.json",
		"_exporter_id": "5784919"
	},
	"item": [
		{
			"name": "find all courses",
			"request": {
				"method": "GET",
				"header": [],
				"url": {
					"raw": "localhost:8082/api/courses",
					"host": [
						"localhost"
					],
					"port": "8082",
					"path": [
						"api",
						"courses"
					]
				}
			},
			"response": [
				{
					"name": "Success",
					"originalRequest": {
						"method": "GET",
						"header": [],
						"url": {
							"raw": "localhost:8082/api/courses",
							"host": [
								"localhost"
							],
							"port": "8082",
							"path": [
								"api",
								"courses"
							]
						}
					},
					"status": "OK",
					"code": 200,
					"_postman_previewlanguage": null,
					"header": null,
					"cookie": [],
					"body": "Request Accepted"
				}
			]
		},
		{
			"name": "find all partants",
			"request": {
				"method": "GET",
				"header": [],
				"url": {
					"raw": "localhost:8082/api/partants",
					"host": [
						"localhost"
					],
					"port": "8082",
					"path": [
						"api",
						"partants"
					]
				}
			},
			"response": [
				{
					"name": "Success",
					"originalRequest": {
						"method": "GET",
						"header": [],
						"url": {
							"raw": "localhost:8082/api/partants",
							"host": [
								"localhost"
							],
							"port": "8082",
							"path": [
								"api",
								"partants"
							]
						}
					},
					"status": "OK",
					"code": 200,
					"_postman_previewlanguage": null,
					"header": null,
					"cookie": [],
					"body": "Request Accepted"
				}
			]
		},
		{
			"name": "create course",
			"request": {
				"method": "POST",
				"header": [],
				"body": {
					"mode": "raw",
					"raw": "{\r\n    \"numero\" : 1561545,\r\n    \"nom\": \"course-test-101\",\r\n    \"jour\": \"2024-02-15\",\r\n    \"partantIds\": [\r\n        123,\r\n        127,\r\n        126\r\n    ]\r\n}",
					"options": {
						"raw": {
							"language": "json"
						}
					}
				},
				"url": {
					"raw": "localhost:8082/api/courses",
					"host": [
						"localhost"
					],
					"port": "8082",
					"path": [
						"api",
						"courses"
					]
				}
			},
			"response": [
				{
					"name": "Success",
					"originalRequest": {
						"method": "POST",
						"header": [
							{
								"key": "Content-Type",
								"name": "Content-Type",
								"value": "application/json",
								"type": "text"
							}
						],
						"body": {
							"mode": "raw",
							"raw": "{\r\n    \"numero\": 1561545,\r\n    \"nom\": \"course-test-101\",\r\n    \"jour\": \"2024-02-15\",\r\n    \"partantIds\": [\r\n        123,\r\n        127,\r\n        126\r\n    ]\r\n}",
							"options": {
								"raw": {
									"language": "json"
								}
							}
						},
						"url": {
							"raw": "localhost:8082/api/courses",
							"host": [
								"localhost"
							],
							"port": "8082",
							"path": [
								"api",
								"courses"
							]
						}
					},
					"status": "OK",
					"code": 200,
					"_postman_previewlanguage": null,
					"header": null,
					"cookie": [],
					"body": "Request Accepted"
				},
				{
					"name": "Bad Request",
					"originalRequest": {
						"method": "POST",
						"header": [
							{
								"key": "Content-Type",
								"name": "Content-Type",
								"value": "application/json",
								"type": "text"
							}
						],
						"body": {
							"mode": "raw",
							"raw": "{\r\n    \"nom\": \"\",\r\n    \"jour\": \"2024-02-15\",\r\n    \"partantIds\": [\r\n        123,\r\n        127,\r\n        126\r\n    ]\r\n}",
							"options": {
								"raw": {
									"language": "json"
								}
							}
						},
						"url": {
							"raw": "localhost:8082/api/courses",
							"host": [
								"localhost"
							],
							"port": "8082",
							"path": [
								"api",
								"courses"
							]
						}
					},
					"status": "Bad Request",
					"code": 400,
					"_postman_previewlanguage": "json",
					"header": [
						{
							"key": "Content-Type",
							"value": "application/json",
							"name": "Content-Type",
							"description": "",
							"type": "text"
						}
					],
					"cookie": [],
					"body": "{\n    \"httpStatus\": 400,\n    \"exception\": \"MethodArgumentNotValidException\",\n    \"message\": \"Paramètres incorrectes\",\n    \"fieldErrors\": [\n        {\n            \"field\": \"champs => message erreur\",\n            \"errorCode\": \"code erreur\"\n        }\n    ]\n}"
				},
				{
					"name": "Internal Server Error",
					"originalRequest": {
						"method": "POST",
						"header": [
							{
								"key": "Content-Type",
								"name": "Content-Type",
								"value": "application/json",
								"type": "text"
							}
						],
						"body": {
							"mode": "raw",
							"raw": "{\r\n    \"numero\": 1561545,\r\n    \"nom\": \"course-test-101\",\r\n    \"jour\": \"2024-02-15\",\r\n    \"partantIds\": [\r\n        123,\r\n        127,\r\n        126\r\n    ]\r\n}",
							"options": {
								"raw": {
									"language": "json"
								}
							}
						},
						"url": {
							"raw": "localhost:8082/api/courses",
							"host": [
								"localhost"
							],
							"port": "8082",
							"path": [
								"api",
								"courses"
							]
						}
					},
					"status": "Bad Request",
					"code": 400,
					"_postman_previewlanguage": "json",
					"header": [
						{
							"key": "Content-Type",
							"value": "application/json",
							"name": "Content-Type",
							"description": "",
							"type": "text"
						}
					],
					"cookie": [],
					"body": "{\n    \"httpStatus\": 500,\n    \"exception\": \"NotSentException\",\n    \"message\": null,\n    \"fieldErrors\": null\n}"
				}
			]
		},
		{
			"name": "create partant",
			"request": {
				"method": "POST",
				"header": [],
				"body": {
					"mode": "raw",
					"raw": "{\r\n    \"numero\" : 15615,\r\n    \"nom\": \"partant-test-101\"\r\n}",
					"options": {
						"raw": {
							"language": "json"
						}
					}
				},
				"url": {
					"raw": "localhost:8082/api/partants",
					"host": [
						"localhost"
					],
					"port": "8082",
					"path": [
						"api",
						"partants"
					]
				}
			},
			"response": [
				{
					"name": "Success",
					"originalRequest": {
						"method": "POST",
						"header": [],
						"body": {
							"mode": "raw",
							"raw": "{\r\n    \"numero\" : 15615,\r\n    \"nom\": \"partant-test-101\"\r\n}",
							"options": {
								"raw": {
									"language": "json"
								}
							}
						},
						"url": {
							"raw": "localhost:8082/api/partants",
							"host": [
								"localhost"
							],
							"port": "8082",
							"path": [
								"api",
								"partants"
							]
						}
					},
					"status": "OK",
					"code": 200,
					"_postman_previewlanguage": null,
					"header": null,
					"cookie": [],
					"body": "Request Accepted"
				},
				{
					"name": "Bad Request",
					"originalRequest": {
						"method": "POST",
						"header": [],
						"body": {
							"mode": "raw",
							"raw": "{\r\n    \"numero\" : \"\",\r\n    \"nom\": \"partant-test-101\"\r\n}",
							"options": {
								"raw": {
									"language": "json"
								}
							}
						},
						"url": {
							"raw": "localhost:8082/api/partants",
							"host": [
								"localhost"
							],
							"port": "8082",
							"path": [
								"api",
								"partants"
							]
						}
					},
					"status": "Bad Request",
					"code": 400,
					"_postman_previewlanguage": "json",
					"header": [
						{
							"key": "Content-Type",
							"value": "application/json",
							"name": "Content-Type",
							"description": "",
							"type": "text"
						}
					],
					"cookie": [],
					"body": "{\n    \"httpStatus\": 400,\n    \"exception\": \"MethodArgumentNotValidException\",\n    \"message\": \"Paramètres incorrectes\",\n    \"fieldErrors\": [\n        {\n            \"field\": \"champs => message erreur\",\n            \"errorCode\": \"code erreur\"\n        }\n    ]\n}"
				},
				{
					"name": "Internal Server Error",
					"originalRequest": {
						"method": "POST",
						"header": [],
						"body": {
							"mode": "raw",
							"raw": "{\r\n    \"numero\" : 15615,\r\n    \"nom\": \"partant-test-101\"\r\n}",
							"options": {
								"raw": {
									"language": "json"
								}
							}
						},
						"url": {
							"raw": "localhost:8082/api/partants",
							"host": [
								"localhost"
							],
							"port": "8082",
							"path": [
								"api",
								"partants"
							]
						}
					},
					"status": "Internal Server Error",
					"code": 500,
					"_postman_previewlanguage": "json",
					"header": [
						{
							"key": "Content-Type",
							"value": "application/json",
							"name": "Content-Type",
							"description": "",
							"type": "text"
						}
					],
					"cookie": [],
					"body": "{\n    \"httpStatus\": 500,\n    \"exception\": \"NotSentException\",\n    \"message\": null,\n    \"fieldErrors\": null\n}"
				}
			]
		}
	]
}